phk_logger/__init__.py
phk_logger/phkLogger.py
phk_logger-0.1.4.dist-info/LICENSE
phk_logger-0.1.4.dist-info/WHEEL
phk_logger-0.1.4.dist-info/METADATA
phk_logger-0.1.4.dist-info/RECORD
