Metadata-Version: 2.1
Name: phk-logger
Version: 0.1.4
Summary: An uncomplicated way to use logger inside python applications
Author: Ben Mz
Author-email: bmz@prohacktive.io
Requires-Python: >=3.6,<4.0
Classifier: Programming Language :: Python :: 3
Classifier: Programming Language :: Python :: 3.6
Classifier: Programming Language :: Python :: 3.7
Classifier: Programming Language :: Python :: 3.8
